incredible/__init__.py
incredible/diagnostics.py
incredible/incredible.py
incredible-0.3.1.dist-info/LICENSE
incredible-0.3.1.dist-info/METADATA
incredible-0.3.1.dist-info/WHEEL
incredible-0.3.1.dist-info/top_level.txt
incredible-0.3.1.dist-info/RECORD
