Metadata-Version: 2.1
Name: incredible
Version: 0.3.1
Summary: incredible
Home-page: https://github.com/abmantz/incredible
Author: Adam Mantz
Author-email: amantz@slac.stanford.edu
License: BSD-3-Clause
Classifier: Development Status :: 4 - Beta
Classifier: Intended Audience :: Science/Research
Classifier: License :: OSI Approved :: BSD License
Classifier: Programming Language :: Python :: 3
License-File: LICENSE
Requires-Dist: numpy
Requires-Dist: scipy
Requires-Dist: matplotlib
Requires-Dist: contourpy
